{
    "actions": [
        {
            "COMMAND": null,
            "RESPONSE": null
        },
        {
            "COMMAND": "[1723794816.895][INFO]: [1563a4a7cfe2583f7f11dea7ada11527] COMMAND InitSession {\n   \"capabilities\": {\n      \"firstMatch\": [ {\n         \"browserName\": \"chrome\",\n         \"goog:chromeOptions\": {\n            \"args\": [ \"--remote-allow-origins=*\" ],\n            \"binary\": \"C:\\\\Program Files\\\\Google\\\\Chrome\\\\Application\\\\chrome.exe\",\n            \"extensions\": [  ]\n         },\n         \"goog:loggingPrefs\": {\n            \"browser\": \"ALL\",\n            \"driver\": \"ALL\"\n         }\n      } ]\n   }\n}\n",
            "RESPONSE": "[1723794817.641][INFO]: [1563a4a7cfe2583f7f11dea7ada11527] RESPONSE InitSession {\n   \"capabilities\": {\n      \"acceptInsecureCerts\": false,\n      \"browserName\": \"chrome\",\n      \"browserVersion\": \"127.0.6533.120\",\n      \"chrome\": {\n         \"chromedriverVersion\": \"127.0.6533.119 (bdef6783a05f0b3f885591e7d2c7b2aec1a89dea-refs/branch-heads/6533@{#1999})\",\n         \"userDataDir\": \"C:\\\\Users\\\\LAKESH~1\\\\AppData\\\\Local\\\\Temp\\\\scoped_dir14828_254212684\"\n      },\n      \"fedcm:accounts\": true,\n      \"goog:chromeOptions\": {\n         \"debuggerAddress\": \"localhost:52024\"\n      },\n      \"networkConnectionEnabled\": false,\n      \"pageLoadStrategy\": \"normal\",\n      \"platformName\": \"windows\",\n      \"proxy\": {\n      },\n      \"setWindowRect\": true,\n      \"strictFileInteractability\": false,\n      \"timeouts\": {\n         \"implicit\": 0,\n         \"pageLoad\": 300000,\n         \"script\": 30000\n      },\n      \"unhandledPromptBehavior\": \"dismiss and notify\",\n      \"webauthn:extension:credBlob\": true,\n      \"webauthn:extension:largeBlob\": true,\n      \"webauthn:extension:minPinLength\": true,\n      \"webauthn:extension:prf\": true,\n      \"webauthn:virtualAuthenticators\": true\n   },\n   \"sessionId\": \"1563a4a7cfe2583f7f11dea7ada11527\"\n}\n"
        },
        {
            "COMMAND": "[1723794817.821][INFO]: [1563a4a7cfe2583f7f11dea7ada11527] COMMAND MaximizeWindow {\n}\n",
            "RESPONSE": "[1723794817.873][INFO]: [1563a4a7cfe2583f7f11dea7ada11527] RESPONSE MaximizeWindow {\n   \"height\": 832,\n   \"width\": 1552,\n   \"x\": -8,\n   \"y\": -8\n}\n"
        },
        {
            "COMMAND": "[1723794817.909][INFO]: [1563a4a7cfe2583f7f11dea7ada11527] COMMAND Navigate {\n   \"url\": \"https://docs.google.com/forms/d/e/1FAIpQLSep9LTMntH5YqIXa5nkiPKSs283kdwitBBhXWyZdAS-e4CxBQ/viewform\"\n}\n",
            "RESPONSE": "[1723794818.862][INFO]: [1563a4a7cfe2583f7f11dea7ada11527] RESPONSE Navigate\n"
        },
        {
            "COMMAND": "[1723794818.894][INFO]: [1563a4a7cfe2583f7f11dea7ada11527] COMMAND FindElement {\n   \"using\": \"xpath\",\n   \"value\": \"//span[text()='Name']/ancestor::div[3]/following-sibling::div//input\"\n}\n",
            "RESPONSE": "[1723794819.976][INFO]: [1563a4a7cfe2583f7f11dea7ada11527] RESPONSE FindElement {\n   \"element-6066-11e4-a52e-4f735466cecf\": \"f.E259C25E75B77B69598EFE641900EE8C.d.AE2FDEBE8A688CA20038FD875699C23E.e.4\"\n}\n"
        },
        {
            "COMMAND": "[1723794821.030][INFO]: [1563a4a7cfe2583f7f11dea7ada11527] COMMAND ClearElement {\n   \"id\": \"f.E259C25E75B77B69598EFE641900EE8C.d.AE2FDEBE8A688CA20038FD875699C23E.e.4\"\n}\n",
            "RESPONSE": "[1723794821.080][INFO]: [1563a4a7cfe2583f7f11dea7ada11527] RESPONSE ClearElement\n"
        },
        {
            "COMMAND": "[1723794821.088][INFO]: [1563a4a7cfe2583f7f11dea7ada11527] COMMAND TypeElement {\n   \"id\": \"f.E259C25E75B77B69598EFE641900EE8C.d.AE2FDEBE8A688CA20038FD875699C23E.e.4\",\n   \"text\": \"Crio Learner\",\n   \"value\": [ \"C\", \"r\", \"i\", \"o\", \" \", \"L\", \"e\", \"a\", \"r\", \"n\", \"e\", \"r\" ]\n}\n",
            "RESPONSE": "[1723794821.359][INFO]: [1563a4a7cfe2583f7f11dea7ada11527] RESPONSE TypeElement\n"
        },
        {
            "COMMAND": "[1723794821.368][INFO]: [1563a4a7cfe2583f7f11dea7ada11527] COMMAND FindElement {\n   \"using\": \"xpath\",\n   \"value\": \"//span[text()='Why are you practicing Automation?']/ancestor::div[3]/following-sibling::div//textarea\"\n}\n",
            "RESPONSE": "[1723794821.424][INFO]: [1563a4a7cfe2583f7f11dea7ada11527] RESPONSE FindElement {\n   \"element-6066-11e4-a52e-4f735466cecf\": \"f.E259C25E75B77B69598EFE641900EE8C.d.AE2FDEBE8A688CA20038FD875699C23E.e.6\"\n}\n"
        },
        {
            "COMMAND": "[1723794821.429][INFO]: [1563a4a7cfe2583f7f11dea7ada11527] COMMAND ClearElement {\n   \"id\": \"f.E259C25E75B77B69598EFE641900EE8C.d.AE2FDEBE8A688CA20038FD875699C23E.e.6\"\n}\n",
            "RESPONSE": "[1723794821.459][INFO]: [1563a4a7cfe2583f7f11dea7ada11527] RESPONSE ClearElement\n"
        },
        {
            "COMMAND": "[1723794821.466][INFO]: [1563a4a7cfe2583f7f11dea7ada11527] COMMAND TypeElement {\n   \"id\": \"f.E259C25E75B77B69598EFE641900EE8C.d.AE2FDEBE8A688CA20038FD875699C23E.e.6\",\n   \"text\": \"I want to be the best QA Engineer! 1723794821429\",\n   \"value\": [ \"I\", \" \", \"w\", \"a\", \"n\", \"t\", \" \", \"t\", \"o\", \" \", \"b\", \"e\", \" \", \"t\", \"h\", \"e\", \" \", \"b\", \"e\", \"s\", \"t\", \" \", \"Q\", \"A\", \" \", \"E\", \"n\", \"g\", \"i\", \"n\", \"e\", \"e\", \"r\", \"!\", \" \", \"1\", \"7\", \"2\", \"3\", \"7\", \"9\", \"4\", \"8\", \"2\", \"1\", \"4\", \"2\", \"9\" ]\n}\n",
            "RESPONSE": "[1723794821.775][INFO]: [1563a4a7cfe2583f7f11dea7ada11527] RESPONSE TypeElement\n"
        },
        {
            "COMMAND": "[1723794821.784][INFO]: [1563a4a7cfe2583f7f11dea7ada11527] COMMAND FindElement {\n   \"using\": \"xpath\",\n   \"value\": \"//span[text()='How much experience do you have in Automation Testing?']/ancestor::div[3]/following-sibling::div//span[text()='0 - 2']/ancestor::div[2]/preceding-sibling::div\"\n}\n",
            "RESPONSE": "[1723794821.803][INFO]: [1563a4a7cfe2583f7f11dea7ada11527] RESPONSE FindElement {\n   \"element-6066-11e4-a52e-4f735466cecf\": \"f.E259C25E75B77B69598EFE641900EE8C.d.AE2FDEBE8A688CA20038FD875699C23E.e.24\"\n}\n"
        },
        {
            "COMMAND": "[1723794821.808][INFO]: [1563a4a7cfe2583f7f11dea7ada11527] COMMAND ClickElement {\n   \"id\": \"f.E259C25E75B77B69598EFE641900EE8C.d.AE2FDEBE8A688CA20038FD875699C23E.e.24\"\n}\n",
            "RESPONSE": "[1723794821.873][INFO]: [1563a4a7cfe2583f7f11dea7ada11527] RESPONSE ClickElement\n"
        },
        {
            "COMMAND": "[1723794821.890][INFO]: [1563a4a7cfe2583f7f11dea7ada11527] COMMAND FindElement {\n   \"using\": \"xpath\",\n   \"value\": \"//span[text()='Which of the following have you learned in Crio.Do for Automation Testing?']/ancestor::div[3]/following-sibling::div//span[text()='Java']/ancestor::div[2]/preceding-sibling::div\"\n}\n",
            "RESPONSE": "[1723794821.910][INFO]: [1563a4a7cfe2583f7f11dea7ada11527] RESPONSE FindElement {\n   \"element-6066-11e4-a52e-4f735466cecf\": \"f.E259C25E75B77B69598EFE641900EE8C.d.AE2FDEBE8A688CA20038FD875699C23E.e.26\"\n}\n"
        },
        {
            "COMMAND": "[1723794821.918][INFO]: [1563a4a7cfe2583f7f11dea7ada11527] COMMAND ClickElement {\n   \"id\": \"f.E259C25E75B77B69598EFE641900EE8C.d.AE2FDEBE8A688CA20038FD875699C23E.e.26\"\n}\n",
            "RESPONSE": "[1723794821.977][INFO]: [1563a4a7cfe2583f7f11dea7ada11527] RESPONSE ClickElement\n"
        },
        {
            "COMMAND": "[1723794821.988][INFO]: [1563a4a7cfe2583f7f11dea7ada11527] COMMAND FindElement {\n   \"using\": \"xpath\",\n   \"value\": \"//span[text()='Which of the following have you learned in Crio.Do for Automation Testing?']/ancestor::div[3]/following-sibling::div//span[text()='Selenium']/ancestor::div[2]/preceding-sibling::div\"\n}\n",
            "RESPONSE": "[1723794822.007][INFO]: [1563a4a7cfe2583f7f11dea7ada11527] RESPONSE FindElement {\n   \"element-6066-11e4-a52e-4f735466cecf\": \"f.E259C25E75B77B69598EFE641900EE8C.d.AE2FDEBE8A688CA20038FD875699C23E.e.27\"\n}\n"
        },
        {
            "COMMAND": "[1723794822.019][INFO]: [1563a4a7cfe2583f7f11dea7ada11527] COMMAND ClickElement {\n   \"id\": \"f.E259C25E75B77B69598EFE641900EE8C.d.AE2FDEBE8A688CA20038FD875699C23E.e.27\"\n}\n",
            "RESPONSE": "[1723794822.062][INFO]: [1563a4a7cfe2583f7f11dea7ada11527] RESPONSE ClickElement\n"
        },
        {
            "COMMAND": "[1723794822.070][INFO]: [1563a4a7cfe2583f7f11dea7ada11527] COMMAND FindElement {\n   \"using\": \"xpath\",\n   \"value\": \"//span[text()='Which of the following have you learned in Crio.Do for Automation Testing?']/ancestor::div[3]/following-sibling::div//span[text()='TestNG']/ancestor::div[2]/preceding-sibling::div\"\n}\n",
            "RESPONSE": "[1723794822.088][INFO]: [1563a4a7cfe2583f7f11dea7ada11527] RESPONSE FindElement {\n   \"element-6066-11e4-a52e-4f735466cecf\": \"f.E259C25E75B77B69598EFE641900EE8C.d.AE2FDEBE8A688CA20038FD875699C23E.e.28\"\n}\n"
        },
        {
            "COMMAND": "[1723794822.091][INFO]: [1563a4a7cfe2583f7f11dea7ada11527] COMMAND ClickElement {\n   \"id\": \"f.E259C25E75B77B69598EFE641900EE8C.d.AE2FDEBE8A688CA20038FD875699C23E.e.28\"\n}\n",
            "RESPONSE": "[1723794822.143][INFO]: [1563a4a7cfe2583f7f11dea7ada11527] RESPONSE ClickElement\n"
        },
        {
            "COMMAND": "[1723794823.649][INFO]: [1563a4a7cfe2583f7f11dea7ada11527] COMMAND FindElement {\n   \"using\": \"xpath\",\n   \"value\": \"//span[text()='How should you be addressed?']/ancestor::div[4]//span[text()='Choose']\"\n}\n",
            "RESPONSE": "[1723794823.669][INFO]: [1563a4a7cfe2583f7f11dea7ada11527] RESPONSE FindElement {\n   \"element-6066-11e4-a52e-4f735466cecf\": \"f.E259C25E75B77B69598EFE641900EE8C.d.AE2FDEBE8A688CA20038FD875699C23E.e.29\"\n}\n"
        },
        {
            "COMMAND": "[1723794823.674][INFO]: [1563a4a7cfe2583f7f11dea7ada11527] COMMAND ClickElement {\n   \"id\": \"f.E259C25E75B77B69598EFE641900EE8C.d.AE2FDEBE8A688CA20038FD875699C23E.e.29\"\n}\n",
            "RESPONSE": "[1723794823.727][INFO]: [1563a4a7cfe2583f7f11dea7ada11527] RESPONSE ClickElement\n"
        },
        {
            "COMMAND": "[1723794825.250][INFO]: [1563a4a7cfe2583f7f11dea7ada11527] COMMAND FindElement {\n   \"using\": \"xpath\",\n   \"value\": \"(//span[text()='How should you be addressed?']/ancestor::div[4]//span[text()='Mr'])[2]\"\n}\n",
            "RESPONSE": "[1723794825.265][INFO]: [1563a4a7cfe2583f7f11dea7ada11527] RESPONSE FindElement {\n   \"element-6066-11e4-a52e-4f735466cecf\": \"f.E259C25E75B77B69598EFE641900EE8C.d.AE2FDEBE8A688CA20038FD875699C23E.e.33\"\n}\n"
        },
        {
            "COMMAND": "[1723794825.294][INFO]: [1563a4a7cfe2583f7f11dea7ada11527] COMMAND ClickElement {\n   \"id\": \"f.E259C25E75B77B69598EFE641900EE8C.d.AE2FDEBE8A688CA20038FD875699C23E.e.33\"\n}\n",
            "RESPONSE": "[1723794825.361][INFO]: [1563a4a7cfe2583f7f11dea7ada11527] RESPONSE ClickElement\n"
        },
        {
            "COMMAND": "[1723794825.410][INFO]: [1563a4a7cfe2583f7f11dea7ada11527] COMMAND FindElement {\n   \"using\": \"xpath\",\n   \"value\": \"//span[text()='What was the date 7 days ago?']/ancestor::div[4]//input\"\n}\n",
            "RESPONSE": "[1723794825.429][INFO]: [1563a4a7cfe2583f7f11dea7ada11527] RESPONSE FindElement {\n   \"element-6066-11e4-a52e-4f735466cecf\": \"f.E259C25E75B77B69598EFE641900EE8C.d.AE2FDEBE8A688CA20038FD875699C23E.e.36\"\n}\n"
        },
        {
            "COMMAND": "[1723794825.445][INFO]: [1563a4a7cfe2583f7f11dea7ada11527] COMMAND TypeElement {\n   \"id\": \"f.E259C25E75B77B69598EFE641900EE8C.d.AE2FDEBE8A688CA20038FD875699C23E.e.36\",\n   \"text\": \"09-08-2024\",\n   \"value\": [ \"0\", \"9\", \"-\", \"0\", \"8\", \"-\", \"2\", \"0\", \"2\", \"4\" ]\n}\n",
            "RESPONSE": "[1723794825.577][INFO]: [1563a4a7cfe2583f7f11dea7ada11527] RESPONSE TypeElement\n"
        },
        {
            "COMMAND": "[1723794825.588][INFO]: [1563a4a7cfe2583f7f11dea7ada11527] COMMAND FindElement {\n   \"using\": \"xpath\",\n   \"value\": \"(//span[text()='What is the time right now?']/ancestor::div[4]//input)[1]\"\n}\n",
            "RESPONSE": "[1723794825.602][INFO]: [1563a4a7cfe2583f7f11dea7ada11527] RESPONSE FindElement {\n   \"element-6066-11e4-a52e-4f735466cecf\": \"f.E259C25E75B77B69598EFE641900EE8C.d.AE2FDEBE8A688CA20038FD875699C23E.e.7\"\n}\n"
        },
        {
            "COMMAND": "[1723794825.608][INFO]: [1563a4a7cfe2583f7f11dea7ada11527] COMMAND TypeElement {\n   \"id\": \"f.E259C25E75B77B69598EFE641900EE8C.d.AE2FDEBE8A688CA20038FD875699C23E.e.7\",\n   \"text\": \"07\",\n   \"value\": [ \"0\", \"7\" ]\n}\n",
            "RESPONSE": "[1723794825.678][INFO]: [1563a4a7cfe2583f7f11dea7ada11527] RESPONSE TypeElement\n"
        },
        {
            "COMMAND": "[1723794825.689][INFO]: [1563a4a7cfe2583f7f11dea7ada11527] COMMAND FindElement {\n   \"using\": \"xpath\",\n   \"value\": \"(//span[text()='What is the time right now?']/ancestor::div[4]//input)[2]\"\n}\n",
            "RESPONSE": "[1723794825.706][INFO]: [1563a4a7cfe2583f7f11dea7ada11527] RESPONSE FindElement {\n   \"element-6066-11e4-a52e-4f735466cecf\": \"f.E259C25E75B77B69598EFE641900EE8C.d.AE2FDEBE8A688CA20038FD875699C23E.e.8\"\n}\n"
        },
        {
            "COMMAND": "[1723794825.711][INFO]: [1563a4a7cfe2583f7f11dea7ada11527] COMMAND TypeElement {\n   \"id\": \"f.E259C25E75B77B69598EFE641900EE8C.d.AE2FDEBE8A688CA20038FD875699C23E.e.8\",\n   \"text\": \"30\",\n   \"value\": [ \"3\", \"0\" ]\n}\n",
            "RESPONSE": "[1723794825.811][INFO]: [1563a4a7cfe2583f7f11dea7ada11527] RESPONSE TypeElement\n"
        },
        {
            "COMMAND": "[1723794825.824][INFO]: [1563a4a7cfe2583f7f11dea7ada11527] COMMAND FindElement {\n   \"using\": \"xpath\",\n   \"value\": \"//span[text()='Submit']\"\n}\n",
            "RESPONSE": "[1723794825.840][INFO]: [1563a4a7cfe2583f7f11dea7ada11527] RESPONSE FindElement {\n   \"element-6066-11e4-a52e-4f735466cecf\": \"f.E259C25E75B77B69598EFE641900EE8C.d.AE2FDEBE8A688CA20038FD875699C23E.e.47\"\n}\n"
        },
        {
            "COMMAND": "[1723794825.863][INFO]: [1563a4a7cfe2583f7f11dea7ada11527] COMMAND ClickElement {\n   \"id\": \"f.E259C25E75B77B69598EFE641900EE8C.d.AE2FDEBE8A688CA20038FD875699C23E.e.47\"\n}\n",
            "RESPONSE": "[1723794827.003][INFO]: [1563a4a7cfe2583f7f11dea7ada11527] RESPONSE ClickElement\n"
        },
        {
            "COMMAND": "[1723794827.022][INFO]: [1563a4a7cfe2583f7f11dea7ada11527] COMMAND FindElement {\n   \"using\": \"xpath\",\n   \"value\": \"//div[text()='Thanks for your response, Automation Wizard!']\"\n}\n",
            "RESPONSE": "[1723794827.037][INFO]: [1563a4a7cfe2583f7f11dea7ada11527] RESPONSE FindElement {\n   \"element-6066-11e4-a52e-4f735466cecf\": \"f.E259C25E75B77B69598EFE641900EE8C.d.820534A7646A7C42A72BAEE4A4067957.e.54\"\n}\n"
        },
        {
            "COMMAND": "[1723794827.061][INFO]: [1563a4a7cfe2583f7f11dea7ada11527] COMMAND GetElementText {\n   \"id\": \"f.E259C25E75B77B69598EFE641900EE8C.d.820534A7646A7C42A72BAEE4A4067957.e.54\"\n}\n",
            "RESPONSE": "[1723794827.084][INFO]: [1563a4a7cfe2583f7f11dea7ada11527] RESPONSE GetElementText \"Thanks for your response, Automation Wizard!\"\n"
        }
    ]
}